sep2tools/__init__.py
sep2tools/__main__.py
sep2tools/cert_create.py
sep2tools/cert_id.py
sep2tools/cert_validate.py
sep2tools/cli.py
sep2tools/events.py
sep2tools/eventsdb.py
sep2tools/examples.py
sep2tools/hexmaps.py
sep2tools/ids.py
sep2tools/models.py
sep2tools/times.py
sep2tools/version.py
sep2tools-0.3.2.dist-info/entry_points.txt
sep2tools-0.3.2.dist-info/LICENSE
sep2tools-0.3.2.dist-info/WHEEL
sep2tools-0.3.2.dist-info/METADATA
sep2tools-0.3.2.dist-info/RECORD
