Metadata-Version: 2.1
Name: sep2tools
Version: 0.3.2
Summary: Useful functions for working with IEEE 2030.5 (SEP2)
Author-email: Alex Guinman <alex@guinman.id.au>
Requires-Python: >=3.11
Classifier: License :: OSI Approved :: MIT License
Classifier: Programming Language :: Python :: 3
Classifier: Programming Language :: Python :: 3.13
Classifier: Programming Language :: Python :: 3.12
Classifier: Programming Language :: Python :: 3.11
Classifier: Operating System :: OS Independent
Requires-Dist: asn1==2.8.0
Requires-Dist: cryptography>=44.0.1
Requires-Dist: pydantic>=2.10.6 
Requires-Dist: python-dateutil>=2.8.2
Requires-Dist: python-dotenv>=1.0.1
Requires-Dist: sqlite_utils>=3.38
Requires-Dist: typer>=0.15.1
Requires-Dist: pytest>=2.7.3 ; extra == "test"
Requires-Dist: pytest-cov>=6.0.0 ; extra == "test"
Requires-Dist: ruff>=0.9.7 ; extra == "test"
Project-URL: Source, https://github.com/aguinane/SEP2-Tools
Provides-Extra: test
